README.md
setup.py
alexmodulo/__init__.py
alexmodulo/cal.py
alexmodulo/pi.py
alexmodulo.egg-info/PKG-INFO
alexmodulo.egg-info/SOURCES.txt
alexmodulo.egg-info/dependency_links.txt
alexmodulo.egg-info/top_level.txt