Metadata-Version: 2.1
Name: alexmodulo
Version: 0.1
Summary: Tarea de modulos de programacion II
Author: Alexander Sanchez
Author-email: alexadersr599@gmail.com
License: MIT
